[
    {
        "background": "none",
        "verlo": "#f5f5f5",
        ".co": "#eeeeee"
    },
    {
        "background": "none",
        "verlo": "#eeeeee",
        ".co": "#e0e0e0"
    },
    {
        "background": "none",
        "verlo": "#e0e0e0",
        ".co": "#bdbdbd"
    },
    {
        "background": "none",
        "verlo": "#bdbdbd",
        ".co": "#9e9e9e"
    },
    {
        "background": "none",
        "verlo": "#d0d0d0",
        ".co": "#c0c0c0"
    },
    {
        "background": "none",
        "verlo": "#c2c2c2",
        ".co": "#b8b8b8"
    },
    {
        "background": "none",
        "verlo": "#b8b8b8",
        ".co": "#aeaeae"
    },
    {
        "background": "none",
        "verlo": "#aeaeae",
        ".co": "#a4a4a4"
    },
    {
        "background": "none",
        "verlo": "#a4a4a4",
        ".co": "#9a9a9a"
    }
]
